omu_chatprovider/__init__.py
omu_chatprovider/__main__.py
omu_chatprovider/chatprovider.py
omu_chatprovider/errors.py
omu_chatprovider/helper.py
omu_chatprovider/service.py
omu_chatprovider/tasks.py
omu_chatprovider/throttle.py
omu_chatprovider/version.py
omu_chatprovider-0.9.50.dist-info/METADATA
omu_chatprovider-0.9.50.dist-info/WHEEL
omu_chatprovider-0.9.50.dist-info/entry_points.txt
omu_chatprovider-0.9.50.dist-info/RECORD
