Metadata-Version: 2.4
Name: omu_chatprovider
Version: 0.9.50
Summary: Add your description here
Author-email: am230 <111672334+am230@users.noreply.github.com>
Requires-Python: >=3.12
Requires-Dist: aiohttp>=3.10.6
Requires-Dist: beautifulsoup4>=4.12.3
Requires-Dist: iwashi>=3.1.0
Requires-Dist: loguru>=0.7.2
Requires-Dist: lxml>=5.0.0
Requires-Dist: omu-chat>=0.9.50
